{
  "scan_utc": "2026-05-18T03:05:30.513881+00:00",
  "source": "GLM-G19",
  "window_minutes": 15,
  "total_volcanoes": 57,
  "red_alerts": 0,
  "yellow_alerts": 0,
  "green_alerts": 57,
  "volcanoes": [
    {
      "volcano": "Acatenango",
      "wwlln_id": "1402-09-",
      "lat": 14.501,
      "lon": -90.876,
      "inner_flashes": 0,
      "outer_flashes": 86,
      "alert": "GREEN",
      "flash_positions": [
        {
          "lat": 15.084890365600586,
          "lon": -91.05294799804688,
          "ring": "outer",
          "time": "2026-05-18T08:00:19+00:00",
          "energy_j": 1.6285085672399483e-14,
          "area_m2": 215168621.71875
        },
        {
          "lat": 15.121706008911133,
          "lon": -91.07725524902344,
          "ring": "outer",
          "time": "2026-05-17T19:49:44+00:00",
          "energy_j": 3.092839078771508e-13,
          "area_m2": 1004883243.984375
        },
        {
          "lat": 15.154052734375,
          "lon": -91.1410903930664,
          "ring": "outer",
          "time": "2026-05-18T08:34:41+00:00",
          "energy_j": 1.7285081652620478e-14,
          "area_m2": 215473825.4375
        },
        {
          "lat": 15.149051666259766,
          "lon": -91.06877136230469,
          "ring": "outer",
          "time": "2026-05-17T18:38:44+00:00",
          "energy_j": 3.428501331637738e-14,
          "area_m2": 215321223.578125
        },
        {
          "lat": 15.076630592346191,
          "lon": -91.05381774902344,
          "ring": "outer",
          "time": "2026-05-17T20:55:16+00:00",
          "energy_j": 1.0285109791073518e-14,
          "area_m2": 358614369.53125
        },
        {
          "lat": 15.126089096069336,
          "lon": -91.07118225097656,
          "ring": "outer",
          "time": "2026-05-18T06:07:00+00:00",
          "energy_j": 4.628496507902931e-14,
          "area_m2": 574088194.96875
        },
        {
          "lat": 15.151435852050781,
          "lon": -91.05812072753906,
          "ring": "outer",
          "time": "2026-05-17T19:33:05+00:00",
          "energy_j": 6.52848887032282e-14,
          "area_m2": 861284894.3125
        },
        {
          "lat": 15.15494441986084,
          "lon": -91.15495300292969,
          "ring": "outer",
          "time": "2026-05-18T11:17:00+00:00",
          "energy_j": 5.728492086146025e-14,
          "area_m2": 431100252.734375
        },
        {
          "lat": 15.14197826385498,
          "lon": -91.06539916992188,
          "ring": "outer",
          "time": "2026-05-17T19:11:54+00:00",
          "energy_j": 5.928491282190224e-14,
          "area_m2": 502517922.921875
        },
        {
          "lat": 15.113155364990234,
          "lon": -91.06352233886719,
          "ring": "outer",
          "time": "2026-05-18T05:55:41+00:00",
          "energy_j": 3.228502135593539e-14,
          "area_m2": 502365321.0625
        },
        {
          "lat": 15.142765998840332,
          "lon": -91.16710662841797,
          "ring": "outer",
          "time": "2026-05-18T09:05:12+00:00",
          "energy_j": 1.2328465555604587e-13,
          "area_m2": 1005951457.0
        },
        {
          "lat": 15.130043029785156,
          "lon": -91.0762939453125,
          "ring": "outer",
          "time": "2026-05-18T09:36:54+00:00",
          "energy_j": 9.285113810852524e-15,
          "area_m2": 287196699.34375
        },
        {
          "lat": 15.129030227661133,
          "lon": -91.0666732788086,
          "ring": "outer",
          "time": "2026-05-17T20:11:16+00:00",
          "energy_j": 4.285133909747552e-15,
          "area_m2": 143598349.671875
        },
        {
          "lat": 15.123311996459961,
          "lon": -91.076416015625,
          "ring": "outer",
          "time": "2026-05-18T09:42:00+00:00",
          "energy_j": 4.0284989197703346e-14,
          "area_m2": 287196699.34375
        },
        {
          "lat": 15.144813537597656,
          "lon": -91.0832290649414,
          "ring": "outer",
          "time": "2026-05-17T21:00:50+00:00",
          "energy_j": 6.328489674278621e-14,
          "area_m2": 287196699.34375
        },
        {
          "lat": 15.148357391357422,
          "lon": -91.147705078125,
          "ring": "outer",
          "time": "2026-05-17T21:29:19+00:00",
          "energy_j": 7.028486860433317e-14,
          "area_m2": 431100252.734375
        },
        {
          "lat": 15.118642807006836,
          "lon": -91.05997467041016,
          "ring": "outer",
          "time": "2026-05-18T07:19:36+00:00",
          "energy_j": 2.6285045474609426e-14,
          "area_m2": 645811068.875
        },
        {
          "lat": 15.14460563659668,
          "lon": -91.0732192993164,
          "ring": "outer",
          "time": "2026-05-17T21:45:15+00:00",
          "energy_j": 1.528508969217849e-14,
          "area_m2": 215321223.578125
        },
        {
          "lat": 15.087287902832031,
          "lon": -91.06776428222656,
          "ring": "outer",
          "time": "2026-05-18T11:35:43+00:00",
          "energy_j": 1.32850977317365e-14,
          "area_m2": 143598349.671875
        },
        {
          "lat": 15.121925354003906,
          "lon": -91.1010971069336,
          "ring": "outer",
          "time": "2026-05-18T01:43:29+00:00",
          "energy_j": 7.128486458455417e-14,
          "area_m2": 430795049.015625
        },
        {
          "lat": 15.159873962402344,
          "lon": -91.06964111328125,
          "ring": "outer",
          "time": "2026-05-17T18:04:10+00:00",
          "energy_j": 2.228506155372545e-14,
          "area_m2": 287196699.34375
        },
        {
          "lat": 15.11810302734375,
          "lon": -91.11748504638672,
          "ring": "outer",
          "time": "2026-05-17T20:49:07+00:00",
          "energy_j": 4.722832526531729e-13,
          "area_m2": 646116272.59375
        },
        {
          "lat": 15.140666961669922,
          "lon": -91.20513916015625,
          "ring": "outer",
          "time": "2026-05-18T10:45:38+00:00",
          "energy_j": 2.2851419493055637e-15,
          "area_m2": 215626427.296875
        },
        {
          "lat": 15.135055541992188,
          "lon": -91.08168029785156,
          "ring": "outer",
          "time": "2026-05-17T22:50:14+00:00",
          "energy_j": 7.728484046588013e-14,
          "area_m2": 287196699.34375
        },
        {
          "lat": 15.146904945373535,
          "lon": -91.15370178222656,
          "ring": "outer",
          "time": "2026-05-18T06:58:49+00:00",
          "energy_j": 1.6285085672399483e-14,
          "area_m2": 287349301.203125
        },
        {
          "lat": 15.13880443572998,
          "lon": -91.09255981445312,
          "ring": "outer",
          "time": "2026-05-18T07:57:58+00:00",
          "energy_j": 4.528496909880832e-14,
          "area_m2": 287196699.34375
        },
        {
          "lat": 15.12729263305664,
          "lon": -91.07853698730469,
          "ring": "outer",
          "time": "2026-05-17T19:16:06+00:00",
          "energy_j": 3.828499723726136e-14,
          "area_m2": 287196699.34375
        },
        {
          "lat": 15.157455444335938,
          "lon": -91.15496063232422,
          "ring": "outer",
          "time": "2026-05-17T20:06:13+00:00",
          "energy_j": 2.5285049494388432e-14,
          "area_m2": 646574078.171875
        },
        {
          "lat": 15.14254093170166,
          "lon": -91.09015655517578,
          "ring": "outer",
          "time": "2026-05-18T00:34:10+00:00",
          "energy_j": 8.928479222853206e-14,
          "area_m2": 287196699.34375
        },
        {
          "lat": 15.131686210632324,
          "lon": -91.08242797851562,
          "ring": "outer",
          "time": "2026-05-18T08:01:18+00:00",
          "energy_j": 3.5285009296598375e-14,
          "area_m2": 287196699.34375
        },
        {
          "lat": 15.158079147338867,
          "lon": -91.06389617919922,
          "ring": "outer",
          "time": "2026-05-17T20:35:21+00:00",
          "energy_j": 3.5285009296598375e-14,
          "area_m2": 717686544.640625
        },
        {
          "lat": 15.166094779968262,
          "lon": -91.13854217529297,
          "ring": "outer",
          "time": "2026-05-17T23:28:12+00:00",
          "energy_j": 1.528508969217849e-14,
          "area_m2": 287349301.203125
        },
        {
          "lat": 15.112977981567383,
          "lon": -91.07186126708984,
          "ring": "outer",
          "time": "2026-05-18T01:46:02+00:00",
          "energy_j": 1.1328469575383593e-13,
          "area_m2": 430642447.15625
        },
        {
          "lat": 15.141066551208496,
          "lon": -91.07373809814453,
          "ring": "outer",
          "time": "2026-05-18T09:28:26+00:00",
          "energy_j": 2.028506959328346e-14,
          "area_m2": 287196699.34375
        },
        {
          "lat": 15.12126350402832,
          "lon": -91.10708618164062,
          "ring": "outer",
          "time": "2026-05-17T18:34:33+00:00",
          "energy_j": 1.6285085672399483e-14,
          "area_m2": 287196699.34375
        },
        {
          "lat": 15.14124870300293,
          "lon": -91.18917846679688,
          "ring": "outer",
          "time": "2026-05-18T07:23:35+00:00",
          "energy_j": 4.128498517792434e-14,
          "area_m2": 790630233.421875
        },
        {
          "lat": 15.154491424560547,
          "lon": -91.07953643798828,
          "ring": "outer",
          "time": "2026-05-18T08:02:56+00:00",
          "energy_j": 3.5285009296598375e-14,
          "area_m2": 287196699.34375
        },
        {
          "lat": 15.119028091430664,
          "lon": -91.15821838378906,
          "ring": "outer",
          "time": "2026-05-18T11:48:30+00:00",
          "energy_j": 1.4285093711957495e-14,
          "area_m2": 287349301.203125
        },
        {
          "lat": 15.133866310119629,
          "lon": -91.09274291992188,
          "ring": "outer",
          "time": "2026-05-17T20:34:43+00:00",
          "energy_j": 5.528492890101826e-14,
          "area_m2": 287196699.34375
        },
        {
          "lat": 15.149090766906738,
          "lon": -91.07495880126953,
          "ring": "outer",
          "time": "2026-05-18T00:48:00+00:00",
          "energy_j": 1.32850977317365e-14,
          "area_m2": 215321223.578125
        },
        {
          "lat": 15.132905960083008,
          "lon": -91.09541320800781,
          "ring": "outer",
          "time": "2026-05-18T08:45:53+00:00",
          "energy_j": 1.6128450280444365e-13,
          "area_m2": 646116272.59375
        },
        {
          "lat": 15.139573097229004,
          "lon": -91.18923950195312,
          "ring": "outer",
          "time": "2026-05-17T20:15:35+00:00",
          "energy_j": 8.628480428786908e-14,
          "area_m2": 1509079787.359375
        },
        {
          "lat": 15.223564147949219,
          "lon": -91.06767272949219,
          "ring": "outer",
          "time": "2026-05-18T00:01:40+00:00",
          "energy_j": 1.16328047498588e-12,
          "area_m2": 4886464139.046875
        },
        {
          "lat": 15.121548652648926,
          "lon": -91.11882781982422,
          "ring": "outer",
          "time": "2026-05-18T07:18:18+00:00",
          "energy_j": 1.8028442642864254e-13,
          "area_m2": 646116272.59375
        },
        {
          "lat": 15.127449989318848,
          "lon": -91.10087585449219,
          "ring": "outer",
          "time": "2026-05-17T18:53:43+00:00",
          "energy_j": 7.285121850410535e-15,
          "area_m2": 287196699.34375
        },
        {
          "lat": 15.151851654052734,
          "lon": -91.09966278076172,
          "ring": "outer",
          "time": "2026-05-17T22:25:02+00:00",
          "energy_j": 3.285137929526558e-15,
          "area_m2": 215473825.4375
        },
        {
          "lat": 15.174027442932129,
          "lon": -91.15471649169922,
          "ring": "outer",
          "time": "2026-05-18T00:19:52+00:00",
          "energy_j": 9.328477614941604e-14,
          "area_m2": 862353107.328125
        },
        {
          "lat": 15.156984329223633,
          "lon": -91.17415618896484,
          "ring": "outer",
          "time": "2026-05-18T10:19:47+00:00",
          "energy_j": 1.532845349626757e-13,
          "area_m2": 934228583.09375
        },
        {
          "lat": 15.12890911102295,
          "lon": -91.0891342163086,
          "ring": "outer",
          "time": "2026-05-17T18:32:50+00:00",
          "energy_j": 9.528476810985803e-14,
          "area_m2": 502365321.0625
        },
        {
          "lat": 15.13719654083252,
          "lon": -91.14612579345703,
          "ring": "outer",
          "time": "2026-05-18T01:41:02+00:00",
          "energy_j": 5.2851298899685465e-15,
          "area_m2": 143598349.671875
        },
        {
          "lat": 15.14691162109375,
          "lon": -91.18383026123047,
          "ring": "outer",
          "time": "2026-05-18T06:33:12+00:00",
          "energy_j": 2.228506155372545e-14,
          "area_m2": 790630233.421875
        },
        {
          "lat": 15.09077262878418,
          "lon": -91.09632873535156,
          "ring": "outer",
          "time": "2026-05-18T07:25:45+00:00",
          "energy_j": 4.2284981158145334e-14,
          "area_m2": 358919573.25
        },
        {
          "lat": 15.13862133026123,
          "lon": -91.09331512451172,
          "ring": "outer",
          "time": "2026-05-17T18:07:50+00:00",
          "energy_j": 1.32850977317365e-14,
          "area_m2": 287196699.34375
        },
        {
          "lat": 15.14585018157959,
          "lon": -91.06900787353516,
          "ring": "outer",
          "time": "2026-05-18T06:45:18+00:00",
          "energy_j": 2.5285049494388432e-14,
          "area_m2": 358919573.25
        },
        {
          "lat": 15.120317459106445,
          "lon": -91.11771392822266,
          "ring": "outer",
          "time": "2026-05-17T18:20:43+00:00",
          "energy_j": 5.828491684168124e-14,
          "area_m2": 430795049.015625
        },
        {
          "lat": 15.133200645446777,
          "lon": -91.08125305175781,
          "ring": "outer",
          "time": "2026-05-17T23:52:05+00:00",
          "energy_j": 1.32850977317365e-14,
          "area_m2": 287196699.34375
        },
        {
          "lat": 15.164778709411621,
          "lon": -91.0874252319336,
          "ring": "outer",
          "time": "2026-05-18T00:44:48+00:00",
          "energy_j": 1.4285093711957495e-14,
          "area_m2": 359072175.109375
        },
        {
          "lat": 15.136674880981445,
          "lon": -91.09207153320312,
          "ring": "outer",
          "time": "2026-05-18T08:41:28+00:00",
          "energy_j": 5.128494498013428e-14,
          "area_m2": 359072175.109375
        },
        {
          "lat": 15.117819786071777,
          "lon": -91.03840637207031,
          "ring": "outer",
          "time": "2026-05-17T18:32:30+00:00",
          "energy_j": 1.32850977317365e-14,
          "area_m2": 573935593.109375
        },
        {
          "lat": 15.148538589477539,
          "lon": -91.0982437133789,
          "ring": "outer",
          "time": "2026-05-18T01:09:52+00:00",
          "energy_j": 3.072839159167088e-13,
          "area_m2": 1149092001.09375
        },
        {
          "lat": 15.143985748291016,
          "lon": -91.10181427001953,
          "ring": "outer",
          "time": "2026-05-18T10:13:54+00:00",
          "energy_j": 7.728484046588013e-14,
          "area_m2": 359072175.109375
        },
        {
          "lat": 15.144176483154297,
          "lon": -91.1065673828125,
          "ring": "outer",
          "time": "2026-05-18T05:50:41+00:00",
          "energy_j": 1.162846836944989e-13,
          "area_m2": 502670524.78125
        },
        {
          "lat": 15.116338729858398,
          "lon": -91.08525848388672,
          "ring": "outer",
          "time": "2026-05-17T18:32:18+00:00",
          "energy_j": 1.1285105771294512e-14,
          "area_m2": 287196699.34375
        },
        {
          "lat": 15.14986515045166,
          "lon": -91.09841918945312,
          "ring": "outer",
          "time": "2026-05-18T01:03:18+00:00",
          "energy_j": 9.628476409007902e-14,
          "area_m2": 574393398.6875
        },
        {
          "lat": 15.139598846435547,
          "lon": -91.09428405761719,
          "ring": "outer",
          "time": "2026-05-17T19:45:20+00:00",
          "energy_j": 3.828499723726136e-14,
          "area_m2": 287196699.34375
        },
        {
          "lat": 15.085715293884277,
          "lon": -91.14360809326172,
          "ring": "outer",
          "time": "2026-05-17T22:42:26+00:00",
          "energy_j": 7.628484448565914e-14,
          "area_m2": 646116272.59375
        },
        {
          "lat": 15.151897430419922,
          "lon": -91.12017822265625,
          "ring": "outer",
          "time": "2026-05-17T23:19:29+00:00",
          "energy_j": 2.6928406866831103e-13,
          "area_m2": 1221120078.71875
        },
        {
          "lat": 15.120200157165527,
          "lon": -91.06782531738281,
          "ring": "outer",
          "time": "2026-05-18T06:51:03+00:00",
          "energy_j": 5.4284932920797266e-14,
          "area_m2": 645811068.875
        },
        {
          "lat": 15.156757354736328,
          "lon": -91.10248565673828,
          "ring": "outer",
          "time": "2026-05-18T00:04:47+00:00",
          "energy_j": 1.7428445054731658e-13,
          "area_m2": 1077369127.1875
        },
        {
          "lat": 15.121026039123535,
          "lon": -91.09634399414062,
          "ring": "outer",
          "time": "2026-05-18T09:25:01+00:00",
          "energy_j": 1.32850977317365e-14,
          "area_m2": 287196699.34375
        },
        {
          "lat": 15.146198272705078,
          "lon": -91.10145568847656,
          "ring": "outer",
          "time": "2026-05-17T21:28:40+00:00",
          "energy_j": 1.528508969217849e-14,
          "area_m2": 287196699.34375
        },
        {
          "lat": 15.133028984069824,
          "lon": -91.10529327392578,
          "ring": "outer",
          "time": "2026-05-18T02:21:47+00:00",
          "energy_j": 1.0228473997140499e-13,
          "area_m2": 502823126.640625
        },
        {
          "lat": 15.13219165802002,
          "lon": -91.10018920898438,
          "ring": "outer",
          "time": "2026-05-17T19:28:42+00:00",
          "energy_j": 1.6528448672532763e-13,
          "area_m2": 574393398.6875
        },
        {
          "lat": 15.13334846496582,
          "lon": -91.09323120117188,
          "ring": "outer",
          "time": "2026-05-17T21:12:00+00:00",
          "energy_j": 3.0528392395626683e-13,
          "area_m2": 718144350.21875
        },
        {
          "lat": 15.128946304321289,
          "lon": -91.10755920410156,
          "ring": "outer",
          "time": "2026-05-17T18:13:16+00:00",
          "energy_j": 2.1028430583527237e-13,
          "area_m2": 861742699.890625
        },
        {
          "lat": 15.117338180541992,
          "lon": -91.10737609863281,
          "ring": "outer",
          "time": "2026-05-18T08:57:18+00:00",
          "energy_j": 6.285125870189541e-15,
          "area_m2": 287196699.34375
        },
        {
          "lat": 15.117463111877441,
          "lon": -91.15911865234375,
          "ring": "outer",
          "time": "2026-05-18T10:47:11+00:00",
          "energy_j": 1.882843942704105e-13,
          "area_m2": 646268874.453125
        },
        {
          "lat": 15.114276885986328,
          "lon": -91.16600036621094,
          "ring": "outer",
          "time": "2026-05-18T10:12:39+00:00",
          "energy_j": 2.8228401641118396e-13,
          "area_m2": 933923379.375
        },
        {
          "lat": 15.086570739746094,
          "lon": -91.1169204711914,
          "ring": "outer",
          "time": "2026-05-18T07:45:19+00:00",
          "energy_j": 1.528508969217849e-14,
          "area_m2": 430642447.15625
        },
        {
          "lat": 15.111510276794434,
          "lon": -91.08482360839844,
          "ring": "outer",
          "time": "2026-05-18T07:48:08+00:00",
          "energy_j": 1.2228465957582488e-13,
          "area_m2": 502365321.0625
        },
        {
          "lat": 15.18891716003418,
          "lon": -91.13223266601562,
          "ring": "outer",
          "time": "2026-05-17T19:53:17+00:00",
          "energy_j": 1.2252802257595816e-12,
          "area_m2": -2099496381.28125
        },
        {
          "lat": 15.132105827331543,
          "lon": -91.10187530517578,
          "ring": "outer",
          "time": "2026-05-18T08:14:04+00:00",
          "energy_j": 9.228478016919505e-14,
          "area_m2": 287196699.34375
        },
        {
          "lat": 15.155826568603516,
          "lon": -91.15045166015625,
          "ring": "outer",
          "time": "2026-05-18T11:45:00+00:00",
          "energy_j": 1.532845349626757e-13,
          "area_m2": 862047903.609375
        },
        {
          "lat": 15.15893840789795,
          "lon": -91.10171508789062,
          "ring": "outer",
          "time": "2026-05-18T02:22:49+00:00",
          "energy_j": 4.428497311858732e-14,
          "area_m2": 502670524.78125
        },
        {
          "lat": 15.120911598205566,
          "lon": -91.10874938964844,
          "ring": "outer",
          "time": "2026-05-17T20:07:27+00:00",
          "energy_j": 1.1028470781317294e-13,
          "area_m2": 646268874.453125
        },
        {
          "lat": 15.155509948730469,
          "lon": -91.20051574707031,
          "ring": "outer",
          "time": "2026-05-17T20:48:58+00:00",
          "energy_j": 8.828479624831107e-14,
          "area_m2": 862353107.328125
        }
      ]
    },
    {
      "volcano": "Fuego",
      "wwlln_id": "1402-10-",
      "lat": 14.473,
      "lon": -90.881,
      "inner_flashes": 0,
      "outer_flashes": 86,
      "alert": "GREEN",
      "flash_positions": [
        {
          "lat": 15.084890365600586,
          "lon": -91.05294799804688,
          "ring": "outer",
          "time": "2026-05-18T08:00:19+00:00",
          "energy_j": 1.6285085672399483e-14,
          "area_m2": 215168621.71875
        },
        {
          "lat": 15.121706008911133,
          "lon": -91.07725524902344,
          "ring": "outer",
          "time": "2026-05-17T19:49:44+00:00",
          "energy_j": 3.092839078771508e-13,
          "area_m2": 1004883243.984375
        },
        {
          "lat": 15.154052734375,
          "lon": -91.1410903930664,
          "ring": "outer",
          "time": "2026-05-18T08:34:41+00:00",
          "energy_j": 1.7285081652620478e-14,
          "area_m2": 215473825.4375
        },
        {
          "lat": 15.149051666259766,
          "lon": -91.06877136230469,
          "ring": "outer",
          "time": "2026-05-17T18:38:44+00:00",
          "energy_j": 3.428501331637738e-14,
          "area_m2": 215321223.578125
        },
        {
          "lat": 15.076630592346191,
          "lon": -91.05381774902344,
          "ring": "outer",
          "time": "2026-05-17T20:55:16+00:00",
          "energy_j": 1.0285109791073518e-14,
          "area_m2": 358614369.53125
        },
        {
          "lat": 15.126089096069336,
          "lon": -91.07118225097656,
          "ring": "outer",
          "time": "2026-05-18T06:07:00+00:00",
          "energy_j": 4.628496507902931e-14,
          "area_m2": 574088194.96875
        },
        {
          "lat": 15.151435852050781,
          "lon": -91.05812072753906,
          "ring": "outer",
          "time": "2026-05-17T19:33:05+00:00",
          "energy_j": 6.52848887032282e-14,
          "area_m2": 861284894.3125
        },
        {
          "lat": 15.15494441986084,
          "lon": -91.15495300292969,
          "ring": "outer",
          "time": "2026-05-18T11:17:00+00:00",
          "energy_j": 5.728492086146025e-14,
          "area_m2": 431100252.734375
        },
        {
          "lat": 15.14197826385498,
          "lon": -91.06539916992188,
          "ring": "outer",
          "time": "2026-05-17T19:11:54+00:00",
          "energy_j": 5.928491282190224e-14,
          "area_m2": 502517922.921875
        },
        {
          "lat": 15.113155364990234,
          "lon": -91.06352233886719,
          "ring": "outer",
          "time": "2026-05-18T05:55:41+00:00",
          "energy_j": 3.228502135593539e-14,
          "area_m2": 502365321.0625
        },
        {
          "lat": 15.142765998840332,
          "lon": -91.16710662841797,
          "ring": "outer",
          "time": "2026-05-18T09:05:12+00:00",
          "energy_j": 1.2328465555604587e-13,
          "area_m2": 1005951457.0
        },
        {
          "lat": 15.130043029785156,
          "lon": -91.0762939453125,
          "ring": "outer",
          "time": "2026-05-18T09:36:54+00:00",
          "energy_j": 9.285113810852524e-15,
          "area_m2": 287196699.34375
        },
        {
          "lat": 15.129030227661133,
          "lon": -91.0666732788086,
          "ring": "outer",
          "time": "2026-05-17T20:11:16+00:00",
          "energy_j": 4.285133909747552e-15,
          "area_m2": 143598349.671875
        },
        {
          "lat": 15.123311996459961,
          "lon": -91.076416015625,
          "ring": "outer",
          "time": "2026-05-18T09:42:00+00:00",
          "energy_j": 4.0284989197703346e-14,
          "area_m2": 287196699.34375
        },
        {
          "lat": 15.144813537597656,
          "lon": -91.0832290649414,
          "ring": "outer",
          "time": "2026-05-17T21:00:50+00:00",
          "energy_j": 6.328489674278621e-14,
          "area_m2": 287196699.34375
        },
        {
          "lat": 15.148357391357422,
          "lon": -91.147705078125,
          "ring": "outer",
          "time": "2026-05-17T21:29:19+00:00",
          "energy_j": 7.028486860433317e-14,
          "area_m2": 431100252.734375
        },
        {
          "lat": 15.118642807006836,
          "lon": -91.05997467041016,
          "ring": "outer",
          "time": "2026-05-18T07:19:36+00:00",
          "energy_j": 2.6285045474609426e-14,
          "area_m2": 645811068.875
        },
        {
          "lat": 15.14460563659668,
          "lon": -91.0732192993164,
          "ring": "outer",
          "time": "2026-05-17T21:45:15+00:00",
          "energy_j": 1.528508969217849e-14,
          "area_m2": 215321223.578125
        },
        {
          "lat": 15.087287902832031,
          "lon": -91.06776428222656,
          "ring": "outer",
          "time": "2026-05-18T11:35:43+00:00",
          "energy_j": 1.32850977317365e-14,
          "area_m2": 143598349.671875
        },
        {
          "lat": 15.121925354003906,
          "lon": -91.1010971069336,
          "ring": "outer",
          "time": "2026-05-18T01:43:29+00:00",
          "energy_j": 7.128486458455417e-14,
          "area_m2": 430795049.015625
        },
        {
          "lat": 15.159873962402344,
          "lon": -91.06964111328125,
          "ring": "outer",
          "time": "2026-05-17T18:04:10+00:00",
          "energy_j": 2.228506155372545e-14,
          "area_m2": 287196699.34375
        },
        {
          "lat": 15.11810302734375,
          "lon": -91.11748504638672,
          "ring": "outer",
          "time": "2026-05-17T20:49:07+00:00",
          "energy_j": 4.722832526531729e-13,
          "area_m2": 646116272.59375
        },
        {
          "lat": 15.140666961669922,
          "lon": -91.20513916015625,
          "ring": "outer",
          "time": "2026-05-18T10:45:38+00:00",
          "energy_j": 2.2851419493055637e-15,
          "area_m2": 215626427.296875
        },
        {
          "lat": 15.135055541992188,
          "lon": -91.08168029785156,
          "ring": "outer",
          "time": "2026-05-17T22:50:14+00:00",
          "energy_j": 7.728484046588013e-14,
          "area_m2": 287196699.34375
        },
        {
          "lat": 15.146904945373535,
          "lon": -91.15370178222656,
          "ring": "outer",
          "time": "2026-05-18T06:58:49+00:00",
          "energy_j": 1.6285085672399483e-14,
          "area_m2": 287349301.203125
        },
        {
          "lat": 15.13880443572998,
          "lon": -91.09255981445312,
          "ring": "outer",
          "time": "2026-05-18T07:57:58+00:00",
          "energy_j": 4.528496909880832e-14,
          "area_m2": 287196699.34375
        },
        {
          "lat": 15.12729263305664,
          "lon": -91.07853698730469,
          "ring": "outer",
          "time": "2026-05-17T19:16:06+00:00",
          "energy_j": 3.828499723726136e-14,
          "area_m2": 287196699.34375
        },
        {
          "lat": 15.157455444335938,
          "lon": -91.15496063232422,
          "ring": "outer",
          "time": "2026-05-17T20:06:13+00:00",
          "energy_j": 2.5285049494388432e-14,
          "area_m2": 646574078.171875
        },
        {
          "lat": 15.14254093170166,
          "lon": -91.09015655517578,
          "ring": "outer",
          "time": "2026-05-18T00:34:10+00:00",
          "energy_j": 8.928479222853206e-14,
          "area_m2": 287196699.34375
        },
        {
          "lat": 15.131686210632324,
          "lon": -91.08242797851562,
          "ring": "outer",
          "time": "2026-05-18T08:01:18+00:00",
          "energy_j": 3.5285009296598375e-14,
          "area_m2": 287196699.34375
        },
        {
          "lat": 15.158079147338867,
          "lon": -91.06389617919922,
          "ring": "outer",
          "time": "2026-05-17T20:35:21+00:00",
          "energy_j": 3.5285009296598375e-14,
          "area_m2": 717686544.640625
        },
        {
          "lat": 15.166094779968262,
          "lon": -91.13854217529297,
          "ring": "outer",
          "time": "2026-05-17T23:28:12+00:00",
          "energy_j": 1.528508969217849e-14,
          "area_m2": 287349301.203125
        },
        {
          "lat": 15.112977981567383,
          "lon": -91.07186126708984,
          "ring": "outer",
          "time": "2026-05-18T01:46:02+00:00",
          "energy_j": 1.1328469575383593e-13,
          "area_m2": 430642447.15625
        },
        {
          "lat": 15.141066551208496,
          "lon": -91.07373809814453,
          "ring": "outer",
          "time": "2026-05-18T09:28:26+00:00",
          "energy_j": 2.028506959328346e-14,
          "area_m2": 287196699.34375
        },
        {
          "lat": 15.12126350402832,
          "lon": -91.10708618164062,
          "ring": "outer",
          "time": "2026-05-17T18:34:33+00:00",
          "energy_j": 1.6285085672399483e-14,
          "area_m2": 287196699.34375
        },
        {
          "lat": 15.14124870300293,
          "lon": -91.18917846679688,
          "ring": "outer",
          "time": "2026-05-18T07:23:35+00:00",
          "energy_j": 4.128498517792434e-14,
          "area_m2": 790630233.421875
        },
        {
          "lat": 15.154491424560547,
          "lon": -91.07953643798828,
          "ring": "outer",
          "time": "2026-05-18T08:02:56+00:00",
          "energy_j": 3.5285009296598375e-14,
          "area_m2": 287196699.34375
        },
        {
          "lat": 15.119028091430664,
          "lon": -91.15821838378906,
          "ring": "outer",
          "time": "2026-05-18T11:48:30+00:00",
          "energy_j": 1.4285093711957495e-14,
          "area_m2": 287349301.203125
        },
        {
          "lat": 15.133866310119629,
          "lon": -91.09274291992188,
          "ring": "outer",
          "time": "2026-05-17T20:34:43+00:00",
          "energy_j": 5.528492890101826e-14,
          "area_m2": 287196699.34375
        },
        {
          "lat": 15.149090766906738,
          "lon": -91.07495880126953,
          "ring": "outer",
          "time": "2026-05-18T00:48:00+00:00",
          "energy_j": 1.32850977317365e-14,
          "area_m2": 215321223.578125
        },
        {
          "lat": 15.132905960083008,
          "lon": -91.09541320800781,
          "ring": "outer",
          "time": "2026-05-18T08:45:53+00:00",
          "energy_j": 1.6128450280444365e-13,
          "area_m2": 646116272.59375
        },
        {
          "lat": 15.139573097229004,
          "lon": -91.18923950195312,
          "ring": "outer",
          "time": "2026-05-17T20:15:35+00:00",
          "energy_j": 8.628480428786908e-14,
          "area_m2": 1509079787.359375
        },
        {
          "lat": 15.223564147949219,
          "lon": -91.06767272949219,
          "ring": "outer",
          "time": "2026-05-18T00:01:40+00:00",
          "energy_j": 1.16328047498588e-12,
          "area_m2": 4886464139.046875
        },
        {
          "lat": 15.121548652648926,
          "lon": -91.11882781982422,
          "ring": "outer",
          "time": "2026-05-18T07:18:18+00:00",
          "energy_j": 1.8028442642864254e-13,
          "area_m2": 646116272.59375
        },
        {
          "lat": 15.127449989318848,
          "lon": -91.10087585449219,
          "ring": "outer",
          "time": "2026-05-17T18:53:43+00:00",
          "energy_j": 7.285121850410535e-15,
          "area_m2": 287196699.34375
        },
        {
          "lat": 15.151851654052734,
          "lon": -91.09966278076172,
          "ring": "outer",
          "time": "2026-05-17T22:25:02+00:00",
          "energy_j": 3.285137929526558e-15,
          "area_m2": 215473825.4375
        },
        {
          "lat": 15.174027442932129,
          "lon": -91.15471649169922,
          "ring": "outer",
          "time": "2026-05-18T00:19:52+00:00",
          "energy_j": 9.328477614941604e-14,
          "area_m2": 862353107.328125
        },
        {
          "lat": 15.156984329223633,
          "lon": -91.17415618896484,
          "ring": "outer",
          "time": "2026-05-18T10:19:47+00:00",
          "energy_j": 1.532845349626757e-13,
          "area_m2": 934228583.09375
        },
        {
          "lat": 15.12890911102295,
          "lon": -91.0891342163086,
          "ring": "outer",
          "time": "2026-05-17T18:32:50+00:00",
          "energy_j": 9.528476810985803e-14,
          "area_m2": 502365321.0625
        },
        {
          "lat": 15.13719654083252,
          "lon": -91.14612579345703,
          "ring": "outer",
          "time": "2026-05-18T01:41:02+00:00",
          "energy_j": 5.2851298899685465e-15,
          "area_m2": 143598349.671875
        },
        {
          "lat": 15.14691162109375,
          "lon": -91.18383026123047,
          "ring": "outer",
          "time": "2026-05-18T06:33:12+00:00",
          "energy_j": 2.228506155372545e-14,
          "area_m2": 790630233.421875
        },
        {
          "lat": 15.09077262878418,
          "lon": -91.09632873535156,
          "ring": "outer",
          "time": "2026-05-18T07:25:45+00:00",
          "energy_j": 4.2284981158145334e-14,
          "area_m2": 358919573.25
        },
        {
          "lat": 15.13862133026123,
          "lon": -91.09331512451172,
          "ring": "outer",
          "time": "2026-05-17T18:07:50+00:00",
          "energy_j": 1.32850977317365e-14,
          "area_m2": 287196699.34375
        },
        {
          "lat": 15.14585018157959,
          "lon": -91.06900787353516,
          "ring": "outer",
          "time": "2026-05-18T06:45:18+00:00",
          "energy_j": 2.5285049494388432e-14,
          "area_m2": 358919573.25
        },
        {
          "lat": 15.120317459106445,
          "lon": -91.11771392822266,
          "ring": "outer",
          "time": "2026-05-17T18:20:43+00:00",
          "energy_j": 5.828491684168124e-14,
          "area_m2": 430795049.015625
        },
        {
          "lat": 15.133200645446777,
          "lon": -91.08125305175781,
          "ring": "outer",
          "time": "2026-05-17T23:52:05+00:00",
          "energy_j": 1.32850977317365e-14,
          "area_m2": 287196699.34375
        },
        {
          "lat": 15.164778709411621,
          "lon": -91.0874252319336,
          "ring": "outer",
          "time": "2026-05-18T00:44:48+00:00",
          "energy_j": 1.4285093711957495e-14,
          "area_m2": 359072175.109375
        },
        {
          "lat": 15.136674880981445,
          "lon": -91.09207153320312,
          "ring": "outer",
          "time": "2026-05-18T08:41:28+00:00",
          "energy_j": 5.128494498013428e-14,
          "area_m2": 359072175.109375
        },
        {
          "lat": 15.117819786071777,
          "lon": -91.03840637207031,
          "ring": "outer",
          "time": "2026-05-17T18:32:30+00:00",
          "energy_j": 1.32850977317365e-14,
          "area_m2": 573935593.109375
        },
        {
          "lat": 15.148538589477539,
          "lon": -91.0982437133789,
          "ring": "outer",
          "time": "2026-05-18T01:09:52+00:00",
          "energy_j": 3.072839159167088e-13,
          "area_m2": 1149092001.09375
        },
        {
          "lat": 15.143985748291016,
          "lon": -91.10181427001953,
          "ring": "outer",
          "time": "2026-05-18T10:13:54+00:00",
          "energy_j": 7.728484046588013e-14,
          "area_m2": 359072175.109375
        },
        {
          "lat": 15.144176483154297,
          "lon": -91.1065673828125,
          "ring": "outer",
          "time": "2026-05-18T05:50:41+00:00",
          "energy_j": 1.162846836944989e-13,
          "area_m2": 502670524.78125
        },
        {
          "lat": 15.116338729858398,
          "lon": -91.08525848388672,
          "ring": "outer",
          "time": "2026-05-17T18:32:18+00:00",
          "energy_j": 1.1285105771294512e-14,
          "area_m2": 287196699.34375
        },
        {
          "lat": 15.14986515045166,
          "lon": -91.09841918945312,
          "ring": "outer",
          "time": "2026-05-18T01:03:18+00:00",
          "energy_j": 9.628476409007902e-14,
          "area_m2": 574393398.6875
        },
        {
          "lat": 15.139598846435547,
          "lon": -91.09428405761719,
          "ring": "outer",
          "time": "2026-05-17T19:45:20+00:00",
          "energy_j": 3.828499723726136e-14,
          "area_m2": 287196699.34375
        },
        {
          "lat": 15.085715293884277,
          "lon": -91.14360809326172,
          "ring": "outer",
          "time": "2026-05-17T22:42:26+00:00",
          "energy_j": 7.628484448565914e-14,
          "area_m2": 646116272.59375
        },
        {
          "lat": 15.151897430419922,
          "lon": -91.12017822265625,
          "ring": "outer",
          "time": "2026-05-17T23:19:29+00:00",
          "energy_j": 2.6928406866831103e-13,
          "area_m2": 1221120078.71875
        },
        {
          "lat": 15.120200157165527,
          "lon": -91.06782531738281,
          "ring": "outer",
          "time": "2026-05-18T06:51:03+00:00",
          "energy_j": 5.4284932920797266e-14,
          "area_m2": 645811068.875
        },
        {
          "lat": 15.156757354736328,
          "lon": -91.10248565673828,
          "ring": "outer",
          "time": "2026-05-18T00:04:47+00:00",
          "energy_j": 1.7428445054731658e-13,
          "area_m2": 1077369127.1875
        },
        {
          "lat": 15.121026039123535,
          "lon": -91.09634399414062,
          "ring": "outer",
          "time": "2026-05-18T09:25:01+00:00",
          "energy_j": 1.32850977317365e-14,
          "area_m2": 287196699.34375
        },
        {
          "lat": 15.146198272705078,
          "lon": -91.10145568847656,
          "ring": "outer",
          "time": "2026-05-17T21:28:40+00:00",
          "energy_j": 1.528508969217849e-14,
          "area_m2": 287196699.34375
        },
        {
          "lat": 15.133028984069824,
          "lon": -91.10529327392578,
          "ring": "outer",
          "time": "2026-05-18T02:21:47+00:00",
          "energy_j": 1.0228473997140499e-13,
          "area_m2": 502823126.640625
        },
        {
          "lat": 15.13219165802002,
          "lon": -91.10018920898438,
          "ring": "outer",
          "time": "2026-05-17T19:28:42+00:00",
          "energy_j": 1.6528448672532763e-13,
          "area_m2": 574393398.6875
        },
        {
          "lat": 15.13334846496582,
          "lon": -91.09323120117188,
          "ring": "outer",
          "time": "2026-05-17T21:12:00+00:00",
          "energy_j": 3.0528392395626683e-13,
          "area_m2": 718144350.21875
        },
        {
          "lat": 15.128946304321289,
          "lon": -91.10755920410156,
          "ring": "outer",
          "time": "2026-05-17T18:13:16+00:00",
          "energy_j": 2.1028430583527237e-13,
          "area_m2": 861742699.890625
        },
        {
          "lat": 15.117338180541992,
          "lon": -91.10737609863281,
          "ring": "outer",
          "time": "2026-05-18T08:57:18+00:00",
          "energy_j": 6.285125870189541e-15,
          "area_m2": 287196699.34375
        },
        {
          "lat": 15.117463111877441,
          "lon": -91.15911865234375,
          "ring": "outer",
          "time": "2026-05-18T10:47:11+00:00",
          "energy_j": 1.882843942704105e-13,
          "area_m2": 646268874.453125
        },
        {
          "lat": 15.114276885986328,
          "lon": -91.16600036621094,
          "ring": "outer",
          "time": "2026-05-18T10:12:39+00:00",
          "energy_j": 2.8228401641118396e-13,
          "area_m2": 933923379.375
        },
        {
          "lat": 15.086570739746094,
          "lon": -91.1169204711914,
          "ring": "outer",
          "time": "2026-05-18T07:45:19+00:00",
          "energy_j": 1.528508969217849e-14,
          "area_m2": 430642447.15625
        },
        {
          "lat": 15.111510276794434,
          "lon": -91.08482360839844,
          "ring": "outer",
          "time": "2026-05-18T07:48:08+00:00",
          "energy_j": 1.2228465957582488e-13,
          "area_m2": 502365321.0625
        },
        {
          "lat": 15.18891716003418,
          "lon": -91.13223266601562,
          "ring": "outer",
          "time": "2026-05-17T19:53:17+00:00",
          "energy_j": 1.2252802257595816e-12,
          "area_m2": -2099496381.28125
        },
        {
          "lat": 15.132105827331543,
          "lon": -91.10187530517578,
          "ring": "outer",
          "time": "2026-05-18T08:14:04+00:00",
          "energy_j": 9.228478016919505e-14,
          "area_m2": 287196699.34375
        },
        {
          "lat": 15.155826568603516,
          "lon": -91.15045166015625,
          "ring": "outer",
          "time": "2026-05-18T11:45:00+00:00",
          "energy_j": 1.532845349626757e-13,
          "area_m2": 862047903.609375
        },
        {
          "lat": 15.15893840789795,
          "lon": -91.10171508789062,
          "ring": "outer",
          "time": "2026-05-18T02:22:49+00:00",
          "energy_j": 4.428497311858732e-14,
          "area_m2": 502670524.78125
        },
        {
          "lat": 15.120911598205566,
          "lon": -91.10874938964844,
          "ring": "outer",
          "time": "2026-05-17T20:07:27+00:00",
          "energy_j": 1.1028470781317294e-13,
          "area_m2": 646268874.453125
        },
        {
          "lat": 15.155509948730469,
          "lon": -91.20051574707031,
          "ring": "outer",
          "time": "2026-05-17T20:48:58+00:00",
          "energy_j": 8.828479624831107e-14,
          "area_m2": 862353107.328125
        }
      ]
    },
    {
      "volcano": "Agua",
      "wwlln_id": "1402-111",
      "lat": 14.466,
      "lon": -90.743,
      "inner_flashes": 0,
      "outer_flashes": 86,
      "alert": "GREEN",
      "flash_positions": [
        {
          "lat": 15.084890365600586,
          "lon": -91.05294799804688,
          "ring": "outer",
          "time": "2026-05-18T08:00:19+00:00",
          "energy_j": 1.6285085672399483e-14,
          "area_m2": 215168621.71875
        },
        {
          "lat": 15.121706008911133,
          "lon": -91.07725524902344,
          "ring": "outer",
          "time": "2026-05-17T19:49:44+00:00",
          "energy_j": 3.092839078771508e-13,
          "area_m2": 1004883243.984375
        },
        {
          "lat": 15.154052734375,
          "lon": -91.1410903930664,
          "ring": "outer",
          "time": "2026-05-18T08:34:41+00:00",
          "energy_j": 1.7285081652620478e-14,
          "area_m2": 215473825.4375
        },
        {
          "lat": 15.149051666259766,
          "lon": -91.06877136230469,
          "ring": "outer",
          "time": "2026-05-17T18:38:44+00:00",
          "energy_j": 3.428501331637738e-14,
          "area_m2": 215321223.578125
        },
        {
          "lat": 15.076630592346191,
          "lon": -91.05381774902344,
          "ring": "outer",
          "time": "2026-05-17T20:55:16+00:00",
          "energy_j": 1.0285109791073518e-14,
          "area_m2": 358614369.53125
        },
        {
          "lat": 15.126089096069336,
          "lon": -91.07118225097656,
          "ring": "outer",
          "time": "2026-05-18T06:07:00+00:00",
          "energy_j": 4.628496507902931e-14,
          "area_m2": 574088194.96875
        },
        {
          "lat": 15.151435852050781,
          "lon": -91.05812072753906,
          "ring": "outer",
          "time": "2026-05-17T19:33:05+00:00",
          "energy_j": 6.52848887032282e-14,
          "area_m2": 861284894.3125
        },
        {
          "lat": 15.15494441986084,
          "lon": -91.15495300292969,
          "ring": "outer",
          "time": "2026-05-18T11:17:00+00:00",
          "energy_j": 5.728492086146025e-14,
          "area_m2": 431100252.734375
        },
        {
          "lat": 15.14197826385498,
          "lon": -91.06539916992188,
          "ring": "outer",
          "time": "2026-05-17T19:11:54+00:00",
          "energy_j": 5.928491282190224e-14,
          "area_m2": 502517922.921875
        },
        {
          "lat": 15.113155364990234,
          "lon": -91.06352233886719,
          "ring": "outer",
          "time": "2026-05-18T05:55:41+00:00",
          "energy_j": 3.228502135593539e-14,
          "area_m2": 502365321.0625
        },
        {
          "lat": 15.142765998840332,
          "lon": -91.16710662841797,
          "ring": "outer",
          "time": "2026-05-18T09:05:12+00:00",
          "energy_j": 1.2328465555604587e-13,
          "area_m2": 1005951457.0
        },
        {
          "lat": 15.130043029785156,
          "lon": -91.0762939453125,
          "ring": "outer",
          "time": "2026-05-18T09:36:54+00:00",
          "energy_j": 9.285113810852524e-15,
          "area_m2": 287196699.34375
        },
        {
          "lat": 15.129030227661133,
          "lon": -91.0666732788086,
          "ring": "outer",
          "time": "2026-05-17T20:11:16+00:00",
          "energy_j": 4.285133909747552e-15,
          "area_m2": 143598349.671875
        },
        {
          "lat": 15.123311996459961,
          "lon": -91.076416015625,
          "ring": "outer",
          "time": "2026-05-18T09:42:00+00:00",
          "energy_j": 4.0284989197703346e-14,
          "area_m2": 287196699.34375
        },
        {
          "lat": 15.144813537597656,
          "lon": -91.0832290649414,
          "ring": "outer",
          "time": "2026-05-17T21:00:50+00:00",
          "energy_j": 6.328489674278621e-14,
          "area_m2": 287196699.34375
        },
        {
          "lat": 15.148357391357422,
          "lon": -91.147705078125,
          "ring": "outer",
          "time": "2026-05-17T21:29:19+00:00",
          "energy_j": 7.028486860433317e-14,
          "area_m2": 431100252.734375
        },
        {
          "lat": 15.118642807006836,
          "lon": -91.05997467041016,
          "ring": "outer",
          "time": "2026-05-18T07:19:36+00:00",
          "energy_j": 2.6285045474609426e-14,
          "area_m2": 645811068.875
        },
        {
          "lat": 15.14460563659668,
          "lon": -91.0732192993164,
          "ring": "outer",
          "time": "2026-05-17T21:45:15+00:00",
          "energy_j": 1.528508969217849e-14,
          "area_m2": 215321223.578125
        },
        {
          "lat": 15.087287902832031,
          "lon": -91.06776428222656,
          "ring": "outer",
          "time": "2026-05-18T11:35:43+00:00",
          "energy_j": 1.32850977317365e-14,
          "area_m2": 143598349.671875
        },
        {
          "lat": 15.121925354003906,
          "lon": -91.1010971069336,
          "ring": "outer",
          "time": "2026-05-18T01:43:29+00:00",
          "energy_j": 7.128486458455417e-14,
          "area_m2": 430795049.015625
        },
        {
          "lat": 15.159873962402344,
          "lon": -91.06964111328125,
          "ring": "outer",
          "time": "2026-05-17T18:04:10+00:00",
          "energy_j": 2.228506155372545e-14,
          "area_m2": 287196699.34375
        },
        {
          "lat": 15.11810302734375,
          "lon": -91.11748504638672,
          "ring": "outer",
          "time": "2026-05-17T20:49:07+00:00",
          "energy_j": 4.722832526531729e-13,
          "area_m2": 646116272.59375
        },
        {
          "lat": 15.140666961669922,
          "lon": -91.20513916015625,
          "ring": "outer",
          "time": "2026-05-18T10:45:38+00:00",
          "energy_j": 2.2851419493055637e-15,
          "area_m2": 215626427.296875
        },
        {
          "lat": 15.135055541992188,
          "lon": -91.08168029785156,
          "ring": "outer",
          "time": "2026-05-17T22:50:14+00:00",
          "energy_j": 7.728484046588013e-14,
          "area_m2": 287196699.34375
        },
        {
          "lat": 15.146904945373535,
          "lon": -91.15370178222656,
          "ring": "outer",
          "time": "2026-05-18T06:58:49+00:00",
          "energy_j": 1.6285085672399483e-14,
          "area_m2": 287349301.203125
        },
        {
          "lat": 15.13880443572998,
          "lon": -91.09255981445312,
          "ring": "outer",
          "time": "2026-05-18T07:57:58+00:00",
          "energy_j": 4.528496909880832e-14,
          "area_m2": 287196699.34375
        },
        {
          "lat": 15.12729263305664,
          "lon": -91.07853698730469,
          "ring": "outer",
          "time": "2026-05-17T19:16:06+00:00",
          "energy_j": 3.828499723726136e-14,
          "area_m2": 287196699.34375
        },
        {
          "lat": 15.157455444335938,
          "lon": -91.15496063232422,
          "ring": "outer",
          "time": "2026-05-17T20:06:13+00:00",
          "energy_j": 2.5285049494388432e-14,
          "area_m2": 646574078.171875
        },
        {
          "lat": 15.14254093170166,
          "lon": -91.09015655517578,
          "ring": "outer",
          "time": "2026-05-18T00:34:10+00:00",
          "energy_j": 8.928479222853206e-14,
          "area_m2": 287196699.34375
        },
        {
          "lat": 15.131686210632324,
          "lon": -91.08242797851562,
          "ring": "outer",
          "time": "2026-05-18T08:01:18+00:00",
          "energy_j": 3.5285009296598375e-14,
          "area_m2": 287196699.34375
        },
        {
          "lat": 15.158079147338867,
          "lon": -91.06389617919922,
          "ring": "outer",
          "time": "2026-05-17T20:35:21+00:00",
          "energy_j": 3.5285009296598375e-14,
          "area_m2": 717686544.640625
        },
        {
          "lat": 15.166094779968262,
          "lon": -91.13854217529297,
          "ring": "outer",
          "time": "2026-05-17T23:28:12+00:00",
          "energy_j": 1.528508969217849e-14,
          "area_m2": 287349301.203125
        },
        {
          "lat": 15.112977981567383,
          "lon": -91.07186126708984,
          "ring": "outer",
          "time": "2026-05-18T01:46:02+00:00",
          "energy_j": 1.1328469575383593e-13,
          "area_m2": 430642447.15625
        },
        {
          "lat": 15.141066551208496,
          "lon": -91.07373809814453,
          "ring": "outer",
          "time": "2026-05-18T09:28:26+00:00",
          "energy_j": 2.028506959328346e-14,
          "area_m2": 287196699.34375
        },
        {
          "lat": 15.12126350402832,
          "lon": -91.10708618164062,
          "ring": "outer",
          "time": "2026-05-17T18:34:33+00:00",
          "energy_j": 1.6285085672399483e-14,
          "area_m2": 287196699.34375
        },
        {
          "lat": 15.14124870300293,
          "lon": -91.18917846679688,
          "ring": "outer",
          "time": "2026-05-18T07:23:35+00:00",
          "energy_j": 4.128498517792434e-14,
          "area_m2": 790630233.421875
        },
        {
          "lat": 15.154491424560547,
          "lon": -91.07953643798828,
          "ring": "outer",
          "time": "2026-05-18T08:02:56+00:00",
          "energy_j": 3.5285009296598375e-14,
          "area_m2": 287196699.34375
        },
        {
          "lat": 15.119028091430664,
          "lon": -91.15821838378906,
          "ring": "outer",
          "time": "2026-05-18T11:48:30+00:00",
          "energy_j": 1.4285093711957495e-14,
          "area_m2": 287349301.203125
        },
        {
          "lat": 15.133866310119629,
          "lon": -91.09274291992188,
          "ring": "outer",
          "time": "2026-05-17T20:34:43+00:00",
          "energy_j": 5.528492890101826e-14,
          "area_m2": 287196699.34375
        },
        {
          "lat": 15.149090766906738,
          "lon": -91.07495880126953,
          "ring": "outer",
          "time": "2026-05-18T00:48:00+00:00",
          "energy_j": 1.32850977317365e-14,
          "area_m2": 215321223.578125
        },
        {
          "lat": 15.132905960083008,
          "lon": -91.09541320800781,
          "ring": "outer",
          "time": "2026-05-18T08:45:53+00:00",
          "energy_j": 1.6128450280444365e-13,
          "area_m2": 646116272.59375
        },
        {
          "lat": 15.139573097229004,
          "lon": -91.18923950195312,
          "ring": "outer",
          "time": "2026-05-17T20:15:35+00:00",
          "energy_j": 8.628480428786908e-14,
          "area_m2": 1509079787.359375
        },
        {
          "lat": 15.223564147949219,
          "lon": -91.06767272949219,
          "ring": "outer",
          "time": "2026-05-18T00:01:40+00:00",
          "energy_j": 1.16328047498588e-12,
          "area_m2": 4886464139.046875
        },
        {
          "lat": 15.121548652648926,
          "lon": -91.11882781982422,
          "ring": "outer",
          "time": "2026-05-18T07:18:18+00:00",
          "energy_j": 1.8028442642864254e-13,
          "area_m2": 646116272.59375
        },
        {
          "lat": 15.127449989318848,
          "lon": -91.10087585449219,
          "ring": "outer",
          "time": "2026-05-17T18:53:43+00:00",
          "energy_j": 7.285121850410535e-15,
          "area_m2": 287196699.34375
        },
        {
          "lat": 15.151851654052734,
          "lon": -91.09966278076172,
          "ring": "outer",
          "time": "2026-05-17T22:25:02+00:00",
          "energy_j": 3.285137929526558e-15,
          "area_m2": 215473825.4375
        },
        {
          "lat": 15.174027442932129,
          "lon": -91.15471649169922,
          "ring": "outer",
          "time": "2026-05-18T00:19:52+00:00",
          "energy_j": 9.328477614941604e-14,
          "area_m2": 862353107.328125
        },
        {
          "lat": 15.156984329223633,
          "lon": -91.17415618896484,
          "ring": "outer",
          "time": "2026-05-18T10:19:47+00:00",
          "energy_j": 1.532845349626757e-13,
          "area_m2": 934228583.09375
        },
        {
          "lat": 15.12890911102295,
          "lon": -91.0891342163086,
          "ring": "outer",
          "time": "2026-05-17T18:32:50+00:00",
          "energy_j": 9.528476810985803e-14,
          "area_m2": 502365321.0625
        },
        {
          "lat": 15.13719654083252,
          "lon": -91.14612579345703,
          "ring": "outer",
          "time": "2026-05-18T01:41:02+00:00",
          "energy_j": 5.2851298899685465e-15,
          "area_m2": 143598349.671875
        },
        {
          "lat": 15.14691162109375,
          "lon": -91.18383026123047,
          "ring": "outer",
          "time": "2026-05-18T06:33:12+00:00",
          "energy_j": 2.228506155372545e-14,
          "area_m2": 790630233.421875
        },
        {
          "lat": 15.09077262878418,
          "lon": -91.09632873535156,
          "ring": "outer",
          "time": "2026-05-18T07:25:45+00:00",
          "energy_j": 4.2284981158145334e-14,
          "area_m2": 358919573.25
        },
        {
          "lat": 15.13862133026123,
          "lon": -91.09331512451172,
          "ring": "outer",
          "time": "2026-05-17T18:07:50+00:00",
          "energy_j": 1.32850977317365e-14,
          "area_m2": 287196699.34375
        },
        {
          "lat": 15.14585018157959,
          "lon": -91.06900787353516,
          "ring": "outer",
          "time": "2026-05-18T06:45:18+00:00",
          "energy_j": 2.5285049494388432e-14,
          "area_m2": 358919573.25
        },
        {
          "lat": 15.120317459106445,
          "lon": -91.11771392822266,
          "ring": "outer",
          "time": "2026-05-17T18:20:43+00:00",
          "energy_j": 5.828491684168124e-14,
          "area_m2": 430795049.015625
        },
        {
          "lat": 15.133200645446777,
          "lon": -91.08125305175781,
          "ring": "outer",
          "time": "2026-05-17T23:52:05+00:00",
          "energy_j": 1.32850977317365e-14,
          "area_m2": 287196699.34375
        },
        {
          "lat": 15.164778709411621,
          "lon": -91.0874252319336,
          "ring": "outer",
          "time": "2026-05-18T00:44:48+00:00",
          "energy_j": 1.4285093711957495e-14,
          "area_m2": 359072175.109375
        },
        {
          "lat": 15.136674880981445,
          "lon": -91.09207153320312,
          "ring": "outer",
          "time": "2026-05-18T08:41:28+00:00",
          "energy_j": 5.128494498013428e-14,
          "area_m2": 359072175.109375
        },
        {
          "lat": 15.117819786071777,
          "lon": -91.03840637207031,
          "ring": "outer",
          "time": "2026-05-17T18:32:30+00:00",
          "energy_j": 1.32850977317365e-14,
          "area_m2": 573935593.109375
        },
        {
          "lat": 15.148538589477539,
          "lon": -91.0982437133789,
          "ring": "outer",
          "time": "2026-05-18T01:09:52+00:00",
          "energy_j": 3.072839159167088e-13,
          "area_m2": 1149092001.09375
        },
        {
          "lat": 15.143985748291016,
          "lon": -91.10181427001953,
          "ring": "outer",
          "time": "2026-05-18T10:13:54+00:00",
          "energy_j": 7.728484046588013e-14,
          "area_m2": 359072175.109375
        },
        {
          "lat": 15.144176483154297,
          "lon": -91.1065673828125,
          "ring": "outer",
          "time": "2026-05-18T05:50:41+00:00",
          "energy_j": 1.162846836944989e-13,
          "area_m2": 502670524.78125
        },
        {
          "lat": 15.116338729858398,
          "lon": -91.08525848388672,
          "ring": "outer",
          "time": "2026-05-17T18:32:18+00:00",
          "energy_j": 1.1285105771294512e-14,
          "area_m2": 287196699.34375
        },
        {
          "lat": 15.14986515045166,
          "lon": -91.09841918945312,
          "ring": "outer",
          "time": "2026-05-18T01:03:18+00:00",
          "energy_j": 9.628476409007902e-14,
          "area_m2": 574393398.6875
        },
        {
          "lat": 15.139598846435547,
          "lon": -91.09428405761719,
          "ring": "outer",
          "time": "2026-05-17T19:45:20+00:00",
          "energy_j": 3.828499723726136e-14,
          "area_m2": 287196699.34375
        },
        {
          "lat": 15.085715293884277,
          "lon": -91.14360809326172,
          "ring": "outer",
          "time": "2026-05-17T22:42:26+00:00",
          "energy_j": 7.628484448565914e-14,
          "area_m2": 646116272.59375
        },
        {
          "lat": 15.151897430419922,
          "lon": -91.12017822265625,
          "ring": "outer",
          "time": "2026-05-17T23:19:29+00:00",
          "energy_j": 2.6928406866831103e-13,
          "area_m2": 1221120078.71875
        },
        {
          "lat": 15.120200157165527,
          "lon": -91.06782531738281,
          "ring": "outer",
          "time": "2026-05-18T06:51:03+00:00",
          "energy_j": 5.4284932920797266e-14,
          "area_m2": 645811068.875
        },
        {
          "lat": 15.156757354736328,
          "lon": -91.10248565673828,
          "ring": "outer",
          "time": "2026-05-18T00:04:47+00:00",
          "energy_j": 1.7428445054731658e-13,
          "area_m2": 1077369127.1875
        },
        {
          "lat": 15.121026039123535,
          "lon": -91.09634399414062,
          "ring": "outer",
          "time": "2026-05-18T09:25:01+00:00",
          "energy_j": 1.32850977317365e-14,
          "area_m2": 287196699.34375
        },
        {
          "lat": 15.146198272705078,
          "lon": -91.10145568847656,
          "ring": "outer",
          "time": "2026-05-17T21:28:40+00:00",
          "energy_j": 1.528508969217849e-14,
          "area_m2": 287196699.34375
        },
        {
          "lat": 15.133028984069824,
          "lon": -91.10529327392578,
          "ring": "outer",
          "time": "2026-05-18T02:21:47+00:00",
          "energy_j": 1.0228473997140499e-13,
          "area_m2": 502823126.640625
        },
        {
          "lat": 15.13219165802002,
          "lon": -91.10018920898438,
          "ring": "outer",
          "time": "2026-05-17T19:28:42+00:00",
          "energy_j": 1.6528448672532763e-13,
          "area_m2": 574393398.6875
        },
        {
          "lat": 15.13334846496582,
          "lon": -91.09323120117188,
          "ring": "outer",
          "time": "2026-05-17T21:12:00+00:00",
          "energy_j": 3.0528392395626683e-13,
          "area_m2": 718144350.21875
        },
        {
          "lat": 15.128946304321289,
          "lon": -91.10755920410156,
          "ring": "outer",
          "time": "2026-05-17T18:13:16+00:00",
          "energy_j": 2.1028430583527237e-13,
          "area_m2": 861742699.890625
        },
        {
          "lat": 15.117338180541992,
          "lon": -91.10737609863281,
          "ring": "outer",
          "time": "2026-05-18T08:57:18+00:00",
          "energy_j": 6.285125870189541e-15,
          "area_m2": 287196699.34375
        },
        {
          "lat": 15.117463111877441,
          "lon": -91.15911865234375,
          "ring": "outer",
          "time": "2026-05-18T10:47:11+00:00",
          "energy_j": 1.882843942704105e-13,
          "area_m2": 646268874.453125
        },
        {
          "lat": 15.114276885986328,
          "lon": -91.16600036621094,
          "ring": "outer",
          "time": "2026-05-18T10:12:39+00:00",
          "energy_j": 2.8228401641118396e-13,
          "area_m2": 933923379.375
        },
        {
          "lat": 15.086570739746094,
          "lon": -91.1169204711914,
          "ring": "outer",
          "time": "2026-05-18T07:45:19+00:00",
          "energy_j": 1.528508969217849e-14,
          "area_m2": 430642447.15625
        },
        {
          "lat": 15.111510276794434,
          "lon": -91.08482360839844,
          "ring": "outer",
          "time": "2026-05-18T07:48:08+00:00",
          "energy_j": 1.2228465957582488e-13,
          "area_m2": 502365321.0625
        },
        {
          "lat": 15.18891716003418,
          "lon": -91.13223266601562,
          "ring": "outer",
          "time": "2026-05-17T19:53:17+00:00",
          "energy_j": 1.2252802257595816e-12,
          "area_m2": -2099496381.28125
        },
        {
          "lat": 15.132105827331543,
          "lon": -91.10187530517578,
          "ring": "outer",
          "time": "2026-05-18T08:14:04+00:00",
          "energy_j": 9.228478016919505e-14,
          "area_m2": 287196699.34375
        },
        {
          "lat": 15.155826568603516,
          "lon": -91.15045166015625,
          "ring": "outer",
          "time": "2026-05-18T11:45:00+00:00",
          "energy_j": 1.532845349626757e-13,
          "area_m2": 862047903.609375
        },
        {
          "lat": 15.15893840789795,
          "lon": -91.10171508789062,
          "ring": "outer",
          "time": "2026-05-18T02:22:49+00:00",
          "energy_j": 4.428497311858732e-14,
          "area_m2": 502670524.78125
        },
        {
          "lat": 15.120911598205566,
          "lon": -91.10874938964844,
          "ring": "outer",
          "time": "2026-05-17T20:07:27+00:00",
          "energy_j": 1.1028470781317294e-13,
          "area_m2": 646268874.453125
        },
        {
          "lat": 15.155509948730469,
          "lon": -91.20051574707031,
          "ring": "outer",
          "time": "2026-05-17T20:48:58+00:00",
          "energy_j": 8.828479624831107e-14,
          "area_m2": 862353107.328125
        }
      ]
    },
    {
      "volcano": "Concepcion (NIC)",
      "wwlln_id": "1404-12-",
      "lat": 11.538,
      "lon": -85.622,
      "inner_flashes": 0,
      "outer_flashes": 0,
      "alert": "GREEN",
      "flash_positions": []
    },
    {
      "volcano": "Maderas (NIC)",
      "wwlln_id": "1404-13-",
      "lat": 11.446,
      "lon": -85.515,
      "inner_flashes": 0,
      "outer_flashes": 0,
      "alert": "GREEN",
      "flash_positions": []
    },
    {
      "volcano": "Orosi (CRI)",
      "wwlln_id": "1405-01-",
      "lat": 10.98,
      "lon": -85.473,
      "inner_flashes": 0,
      "outer_flashes": 0,
      "alert": "GREEN",
      "flash_positions": []
    },
    {
      "volcano": "Rincon de la Vieja (CRI)",
      "wwlln_id": "1405-02-",
      "lat": 10.83,
      "lon": -85.324,
      "inner_flashes": 0,
      "outer_flashes": 0,
      "alert": "GREEN",
      "flash_positions": []
    },
    {
      "volcano": "Taapaca",
      "wwlln_id": "1505-011",
      "lat": -18.109,
      "lon": -69.506,
      "inner_flashes": 0,
      "outer_flashes": 0,
      "alert": "GREEN",
      "flash_positions": []
    },
    {
      "volcano": "Parinacota",
      "wwlln_id": "1505-012",
      "lat": -18.171,
      "lon": -69.145,
      "inner_flashes": 0,
      "outer_flashes": 0,
      "alert": "GREEN",
      "flash_positions": []
    },
    {
      "volcano": "Guallatiri",
      "wwlln_id": "1505-02-",
      "lat": -18.428,
      "lon": -69.085,
      "inner_flashes": 0,
      "outer_flashes": 0,
      "alert": "GREEN",
      "flash_positions": []
    },
    {
      "volcano": "Isluga",
      "wwlln_id": "1505-03-",
      "lat": -19.167,
      "lon": -68.822,
      "inner_flashes": 0,
      "outer_flashes": 0,
      "alert": "GREEN",
      "flash_positions": []
    },
    {
      "volcano": "Irruputuncu",
      "wwlln_id": "1505-04-",
      "lat": -20.733,
      "lon": -68.56,
      "inner_flashes": 0,
      "outer_flashes": 0,
      "alert": "GREEN",
      "flash_positions": []
    },
    {
      "volcano": "Ollague",
      "wwlln_id": "1505-06-",
      "lat": -21.307,
      "lon": -68.179,
      "inner_flashes": 0,
      "outer_flashes": 0,
      "alert": "GREEN",
      "flash_positions": []
    },
    {
      "volcano": "San Pedro",
      "wwlln_id": "1505-07-",
      "lat": -21.885,
      "lon": -68.407,
      "inner_flashes": 0,
      "outer_flashes": 0,
      "alert": "GREEN",
      "flash_positions": []
    },
    {
      "volcano": "Lascar",
      "wwlln_id": "1505-10-",
      "lat": -23.367,
      "lon": -67.736,
      "inner_flashes": 0,
      "outer_flashes": 0,
      "alert": "GREEN",
      "flash_positions": []
    },
    {
      "volcano": "Tupungatito",
      "wwlln_id": "1507-01-",
      "lat": -33.408,
      "lon": -69.822,
      "inner_flashes": 0,
      "outer_flashes": 0,
      "alert": "GREEN",
      "flash_positions": []
    },
    {
      "volcano": "San Jose",
      "wwlln_id": "1507-02-",
      "lat": -33.787,
      "lon": -69.897,
      "inner_flashes": 0,
      "outer_flashes": 0,
      "alert": "GREEN",
      "flash_positions": []
    },
    {
      "volcano": "Tinguiririca",
      "wwlln_id": "1507-03-",
      "lat": -34.808,
      "lon": -70.349,
      "inner_flashes": 0,
      "outer_flashes": 0,
      "alert": "GREEN",
      "flash_positions": []
    },
    {
      "volcano": "Planchon-Peteroa",
      "wwlln_id": "1507-04-",
      "lat": -35.242,
      "lon": -70.572,
      "inner_flashes": 0,
      "outer_flashes": 0,
      "alert": "GREEN",
      "flash_positions": []
    },
    {
      "volcano": "Descabezado Grande",
      "wwlln_id": "1507-05-",
      "lat": -35.604,
      "lon": -70.748,
      "inner_flashes": 0,
      "outer_flashes": 0,
      "alert": "GREEN",
      "flash_positions": []
    },
    {
      "volcano": "Tatara-San Pedro",
      "wwlln_id": "1507-062",
      "lat": -35.998,
      "lon": -70.845,
      "inner_flashes": 0,
      "outer_flashes": 0,
      "alert": "GREEN",
      "flash_positions": []
    },
    {
      "volcano": "Laguna del Maule",
      "wwlln_id": "1507-061",
      "lat": -36.071,
      "lon": -70.498,
      "inner_flashes": 0,
      "outer_flashes": 0,
      "alert": "GREEN",
      "flash_positions": []
    },
    {
      "volcano": "Nevado de Longavi",
      "wwlln_id": "1507-063",
      "lat": -36.2,
      "lon": -71.17,
      "inner_flashes": 0,
      "outer_flashes": 0,
      "alert": "GREEN",
      "flash_positions": []
    },
    {
      "volcano": "Nevados de Chillan",
      "wwlln_id": "1507-07-",
      "lat": -37.411,
      "lon": -71.352,
      "inner_flashes": 0,
      "outer_flashes": 0,
      "alert": "GREEN",
      "flash_positions": []
    },
    {
      "volcano": "Antuco",
      "wwlln_id": "1507-08-",
      "lat": -37.419,
      "lon": -71.341,
      "inner_flashes": 0,
      "outer_flashes": 0,
      "alert": "GREEN",
      "flash_positions": []
    },
    {
      "volcano": "Copahue",
      "wwlln_id": "1507-09-",
      "lat": -37.857,
      "lon": -71.168,
      "inner_flashes": 0,
      "outer_flashes": 0,
      "alert": "GREEN",
      "flash_positions": []
    },
    {
      "volcano": "Callaqui",
      "wwlln_id": "1507-091",
      "lat": -37.926,
      "lon": -71.461,
      "inner_flashes": 0,
      "outer_flashes": 0,
      "alert": "GREEN",
      "flash_positions": []
    },
    {
      "volcano": "Lonquimay",
      "wwlln_id": "1507-10-",
      "lat": -38.382,
      "lon": -71.585,
      "inner_flashes": 0,
      "outer_flashes": 0,
      "alert": "GREEN",
      "flash_positions": []
    },
    {
      "volcano": "Llaima",
      "wwlln_id": "1507-11-",
      "lat": -38.712,
      "lon": -71.734,
      "inner_flashes": 0,
      "outer_flashes": 0,
      "alert": "GREEN",
      "flash_positions": []
    },
    {
      "volcano": "Sollipulli",
      "wwlln_id": "1507-111",
      "lat": -38.981,
      "lon": -71.516,
      "inner_flashes": 0,
      "outer_flashes": 0,
      "alert": "GREEN",
      "flash_positions": []
    },
    {
      "volcano": "Villarrica",
      "wwlln_id": "1507-12-",
      "lat": -39.421,
      "lon": -71.939,
      "inner_flashes": 0,
      "outer_flashes": 0,
      "alert": "GREEN",
      "flash_positions": []
    },
    {
      "volcano": "Quetrupillan",
      "wwlln_id": "1507-121",
      "lat": -39.532,
      "lon": -71.703,
      "inner_flashes": 0,
      "outer_flashes": 0,
      "alert": "GREEN",
      "flash_positions": []
    },
    {
      "volcano": "Lanin",
      "wwlln_id": "1507-122",
      "lat": -39.628,
      "lon": -71.479,
      "inner_flashes": 0,
      "outer_flashes": 0,
      "alert": "GREEN",
      "flash_positions": []
    },
    {
      "volcano": "Mocho-Choshuenco",
      "wwlln_id": "1507-13-",
      "lat": -39.934,
      "lon": -72.003,
      "inner_flashes": 0,
      "outer_flashes": 0,
      "alert": "GREEN",
      "flash_positions": []
    },
    {
      "volcano": "Carran - Los Venados",
      "wwlln_id": "1507-14-",
      "lat": -40.379,
      "lon": -72.105,
      "inner_flashes": 0,
      "outer_flashes": 0,
      "alert": "GREEN",
      "flash_positions": []
    },
    {
      "volcano": "Puyehue - Cordon Caulle",
      "wwlln_id": "1507-15-",
      "lat": -40.559,
      "lon": -72.125,
      "inner_flashes": 0,
      "outer_flashes": 0,
      "alert": "GREEN",
      "flash_positions": []
    },
    {
      "volcano": "Antillanca - Casablanca",
      "wwlln_id": "1507-153",
      "lat": -40.771,
      "lon": -72.153,
      "inner_flashes": 0,
      "outer_flashes": 0,
      "alert": "GREEN",
      "flash_positions": []
    },
    {
      "volcano": "Osorno",
      "wwlln_id": "1508-01-",
      "lat": -41.135,
      "lon": -72.497,
      "inner_flashes": 0,
      "outer_flashes": 0,
      "alert": "GREEN",
      "flash_positions": []
    },
    {
      "volcano": "Calbuco",
      "wwlln_id": "1508-02-",
      "lat": -41.329,
      "lon": -72.611,
      "inner_flashes": 0,
      "outer_flashes": 0,
      "alert": "GREEN",
      "flash_positions": []
    },
    {
      "volcano": "Yate",
      "wwlln_id": "1508-022",
      "lat": -41.755,
      "lon": -72.396,
      "inner_flashes": 0,
      "outer_flashes": 0,
      "alert": "GREEN",
      "flash_positions": []
    },
    {
      "volcano": "Hornopiren",
      "wwlln_id": "1508-023",
      "lat": -41.874,
      "lon": -72.431,
      "inner_flashes": 0,
      "outer_flashes": 0,
      "alert": "GREEN",
      "flash_positions": []
    },
    {
      "volcano": "Huequi",
      "wwlln_id": "1508-03-",
      "lat": -42.378,
      "lon": -72.578,
      "inner_flashes": 0,
      "outer_flashes": 0,
      "alert": "GREEN",
      "flash_positions": []
    },
    {
      "volcano": "Michinmahuida",
      "wwlln_id": "1508-04-",
      "lat": -42.79,
      "lon": -72.44,
      "inner_flashes": 0,
      "outer_flashes": 0,
      "alert": "GREEN",
      "flash_positions": []
    },
    {
      "volcano": "Chaiten",
      "wwlln_id": "1508-041",
      "lat": -42.839,
      "lon": -72.65,
      "inner_flashes": 0,
      "outer_flashes": 0,
      "alert": "GREEN",
      "flash_positions": []
    },
    {
      "volcano": "Corcovado",
      "wwlln_id": "1508-05-",
      "lat": -43.192,
      "lon": -72.079,
      "inner_flashes": 0,
      "outer_flashes": 0,
      "alert": "GREEN",
      "flash_positions": []
    },
    {
      "volcano": "Melimoyu",
      "wwlln_id": "1508-052",
      "lat": -44.081,
      "lon": -72.857,
      "inner_flashes": 0,
      "outer_flashes": 0,
      "alert": "GREEN",
      "flash_positions": []
    },
    {
      "volcano": "Mentolat",
      "wwlln_id": "1508-054",
      "lat": -44.7,
      "lon": -73.082,
      "inner_flashes": 0,
      "outer_flashes": 0,
      "alert": "GREEN",
      "flash_positions": []
    },
    {
      "volcano": "Cay",
      "wwlln_id": "1508-055",
      "lat": -45.059,
      "lon": -72.984,
      "inner_flashes": 0,
      "outer_flashes": 0,
      "alert": "GREEN",
      "flash_positions": []
    },
    {
      "volcano": "Maca",
      "wwlln_id": "1508-056",
      "lat": -45.1,
      "lon": -73.174,
      "inner_flashes": 0,
      "outer_flashes": 0,
      "alert": "GREEN",
      "flash_positions": []
    },
    {
      "volcano": "Hudson",
      "wwlln_id": "1508-057",
      "lat": -45.9,
      "lon": -72.97,
      "inner_flashes": 0,
      "outer_flashes": 0,
      "alert": "GREEN",
      "flash_positions": []
    },
    {
      "volcano": "Wai Sano (IDN)",
      "wwlln_id": "0604-06-",
      "lat": -8.72,
      "lon": 120.02,
      "inner_flashes": 0,
      "outer_flashes": 0,
      "alert": "GREEN",
      "flash_positions": []
    },
    {
      "volcano": "Ranakah (IDN)",
      "wwlln_id": "0604-071",
      "lat": -8.62,
      "lon": 120.52,
      "inner_flashes": 0,
      "outer_flashes": 0,
      "alert": "GREEN",
      "flash_positions": []
    },
    {
      "volcano": "Ambrym (VUT)",
      "wwlln_id": "0507-04-",
      "lat": -16.25,
      "lon": 168.12,
      "inner_flashes": 0,
      "outer_flashes": 0,
      "alert": "GREEN",
      "flash_positions": []
    },
    {
      "volcano": "Jingbo (CHN)",
      "wwlln_id": "1005-04-",
      "lat": 44.08,
      "lon": 128.83,
      "inner_flashes": 0,
      "outer_flashes": 0,
      "alert": "GREEN",
      "flash_positions": []
    },
    {
      "volcano": "Kishb Harrat (SAU)",
      "wwlln_id": "0301-071",
      "lat": 22.8,
      "lon": 41.38,
      "inner_flashes": 0,
      "outer_flashes": 0,
      "alert": "GREEN",
      "flash_positions": []
    },
    {
      "volcano": "Semeru (IDN)",
      "wwlln_id": "0603-30-",
      "lat": -8.108,
      "lon": 112.92,
      "inner_flashes": 0,
      "outer_flashes": 0,
      "alert": "GREEN",
      "flash_positions": []
    },
    {
      "volcano": "Kavachi (SLB)",
      "wwlln_id": "0505-06-",
      "lat": -9.02,
      "lon": 157.95,
      "inner_flashes": 0,
      "outer_flashes": 0,
      "alert": "GREEN",
      "flash_positions": []
    }
  ]
}